LICENSE
README.md
setup.py
promptdesignerdataset/__init__.py
promptdesignerdataset/dataset.py
promptdesignerdataset.egg-info/PKG-INFO
promptdesignerdataset.egg-info/SOURCES.txt
promptdesignerdataset.egg-info/dependency_links.txt
promptdesignerdataset.egg-info/top_level.txt