Metadata-Version: 2.1
Name: promptdesignerdataset
Version: 0.0.1a0
Summary: my test
Home-page: http://www.example.com/it
Author: Patrizio Bellan
Author-email: patrizio.bellan@gmail.com
License: MIT
Platform: UNKNOWN
Classifier: License :: OSI Approved :: MIT License
Classifier: Programming Language :: Python :: 3
License-File: LICENSE
